ShadiX/__init__.py
ShadiX/clientData.py
ShadiX/creator.py
ShadiX/encrypt.py
ShadiX/getServer.py
ShadiX/message.py
ShadiX/method.py
ShadiX/requestMaker.py
ShadiX/socketHandler.py
ShadiX-1.0.1.dist-info/LICENCE
ShadiX-1.0.1.dist-info/METADATA
ShadiX-1.0.1.dist-info/WHEEL
ShadiX-1.0.1.dist-info/top_level.txt
ShadiX-1.0.1.dist-info/RECORD
